{
  "voiceline_id": "patron_female_ally_forge_start_03",
  "timestamp": "2025-03-12T12:49:18.978858",
  "segments": [
    {
      "start": 0.0,
      "end": 3.799999952316284,
      "text": " Fairfax Industries is wasting your talents, McGinnis.",
      "part": 1
    },
    {
      "start": 3.799999952316284,
      "end": 5.699999809265137,
      "text": " You deserve better.",
      "part": 2
    },
    {
      "start": 5.699999809265137,
      "end": 9.199999809265137,
      "text": " And I can provide that for you.",
      "part": 3
    }
  ]
}